{
  "id": "love-capitalization",
  "name": "좋은 소식 어떻게 나누나요",
  "subtitle": "기쁜 일을 연인과 나누는 방식을 탐색하는 심리 게임",
  "description": "좋은 일이 생겼을 때, 그것을 누군가와 나누는 방식은 사람마다 다릅니다. 어떤 사람은 즉시 전화를 걸고, 어떤 사람은 조용히 곱씹으며, 어떤 사람은 현실적 의미를 먼저 따집니다. 당신이 기쁨을 연인과 공유하는 고유한 스타일을 살펴보세요. 6가지 상황에서 가장 자연스럽게 느껴지는 선택을 골라주세요. 정답은 없습니다. 어떤 공유 방식이든 관계에 기여하는 고유한 강점이 있습니다.",
  "emoji": "🎉",
  "theory": "Capitalization Process (자본화 과정 이론)",
  "theoryRef": "Gable, S. L., Reis, H. T., Impett, E. A., & Asher, E. R. (2004). What do you do when things go right? The intrapersonal and interpersonal benefits of sharing positive events. Journal of Personality and Social Psychology, 87(2), 228-245.",
  "exp": 40,
  "questions": [
    {
      "id": "q1",
      "situation": "오랫동안 준비한 자격증 시험에 합격했습니다. 결과를 확인한 직후 연인에게 소식을 전하는 당신의 방식은...",
      "choices": [
        { "id": "A", "text": "바로 전화해서 '나 합격했어!'라고 말한다. 상대의 축하 반응을 듣고 싶고, 함께 기뻐하며 오늘 저녁 축하 약속을 잡고 싶다." },
        { "id": "B", "text": "혼자 잠깐 기쁨을 느낀 뒤, 만났을 때 조용히 이야기한다. 합격의 의미를 천천히 나누면서 상대와 깊이 있는 대화를 하고 싶다." },
        { "id": "C", "text": "합격 소식과 함께 이제 어떤 기회가 열리는지도 이야기한다. 커리어 계획에 어떤 영향을 주는지 연인과 현실적으로 대화해보고 싶다." }
      ]
    },
    {
      "id": "q2",
      "situation": "회사에서 예상치 못한 승진 소식을 들었습니다. 연인에게 이 소식을 전할 때 당신이 가장 기대하는 것은...",
      "choices": [
        { "id": "A", "text": "상대가 나만큼 기뻐해주는 것. 같이 흥분하고, '대단하다', '역시 너야'라는 말을 듣고 싶다. 기쁨이 두 배가 되는 느낌이 좋다." },
        { "id": "B", "text": "상대와 나란히 앉아 승진까지의 과정을 되돌아보는 시간. 힘들었던 순간을 함께 떠올리면서 '우리가 여기까지 왔구나'라고 느끼고 싶다." },
        { "id": "C", "text": "승진에 따라 달라지는 업무 환경이나 수입 변화를 함께 정리해보는 것. 좋은 소식을 실질적 계획으로 연결하는 대화를 나누고 싶다." }
      ]
    },
    {
      "id": "q3",
      "situation": "좋아하는 아티스트의 콘서트 티켓팅에 성공했습니다. 연인에게 이 소식을 전하면서 당신이 자연스럽게 하는 행동은...",
      "choices": [
        { "id": "A", "text": "화면을 캡처해서 바로 보내며 '떴다!'라고 흥분한다. 상대가 함께 좋아해주면 기쁨이 더 커지고, 콘서트 날까지 같이 설레고 싶다." },
        { "id": "B", "text": "티켓팅 성공의 기쁨을 잠시 혼자 만끽한 뒤, 만났을 때 자연스럽게 이야기한다. 상대의 표정을 보면서 나누는 것이 더 좋다." },
        { "id": "C", "text": "소식을 전하면서 동시에 그날 일정 조율을 시작한다. 누가 같이 갈지, 교통편은 어떻게 할지 구체적으로 정리하고 싶다." }
      ]
    },
    {
      "id": "q4",
      "situation": "건강검진 결과가 모두 정상으로 나왔습니다. 특별히 걱정했던 수치도 괜찮았습니다. 연인에게 이 소식을 전할 때 당신은...",
      "choices": [
        { "id": "A", "text": "바로 연락해서 '다 정상이래!'라고 말한다. 상대도 나처럼 안도하고 기뻐할 것을 알기에, 그 감정을 실시간으로 나누고 싶다." },
        { "id": "B", "text": "결과를 확인하고 혼자 안도의 시간을 가진 뒤, 만나서 이야기한다. 건강에 대해 서로가 느끼는 것을 차분하게 나누고 싶다." },
        { "id": "C", "text": "검진 결과를 보여주면서, 앞으로 건강 관리를 어떻게 할지 함께 계획을 세워보자고 제안한다. 이번 기회에 운동이나 식단도 정리하고 싶다." }
      ]
    },
    {
      "id": "q5",
      "situation": "오래 지원했던 사이드 프로젝트에 최종 선정되었습니다. 이 소식을 연인에게 전하면서 당신이 가장 중요하게 생각하는 것은...",
      "choices": [
        { "id": "A", "text": "상대가 내 도전을 함께 응원해왔으니, 이 결과를 같이 축하하는 순간을 만들고 싶다. 특별한 저녁이나 작은 파티를 제안한다." },
        { "id": "B", "text": "선정까지의 과정에서 느꼈던 불안, 설렘, 기대를 상대와 나누고 싶다. 결과보다 그 과정을 함께 되돌아보는 시간이 더 의미 있다." },
        { "id": "C", "text": "프로젝트 일정과 기존 생활 패턴을 어떻게 조율할지 상대와 미리 이야기한다. 서로의 시간에 영향을 줄 수 있으니 계획을 공유하고 싶다." }
      ]
    },
    {
      "id": "q6",
      "situation": "친구가 '너 좋은 일 있을 때 연인한테 먼저 말해?'라고 물었습니다. 생각해보니 당신의 패턴은...",
      "choices": [
        { "id": "A", "text": "거의 항상 연인에게 먼저 말한다. 좋은 일을 나눌 때 상대가 함께 기뻐해주는 것 자체가 그 기쁨을 완성시켜주는 느낌이다." },
        { "id": "B", "text": "바로 말하기보다 혼자 소화하는 시간을 가진 뒤에 나눈다. 기쁨의 의미를 충분히 느끼고 나서 상대와 깊이 있게 이야기하는 것이 좋다." },
        { "id": "C", "text": "소식을 전하면서 자연스럽게 다음 단계 이야기를 한다. 좋은 일이 생기면 그것을 어떻게 잘 활용할지 함께 계획하는 것이 내 스타일이다." }
      ]
    }
  ],
  "scoring": {
    "rules": [
      { "condition": "A >= 4", "result": "ACTIVE_CONSTRUCTIVE" },
      { "condition": "B >= 4", "result": "QUIET_SAVORING" },
      { "condition": "C >= 4", "result": "PRACTICAL_GROUNDING" },
      { "default": true, "result": "RESERVED_PROCESSING" }
    ]
  },
  "results": {
    "ACTIVE_CONSTRUCTIVE": {
      "emoji": "🥳",
      "title": "적극적-구성적 반응형",
      "description": "당신은 좋은 일이 생기면 연인과 즉시, 그리고 적극적으로 나누는 사람입니다. 기쁨을 표현하고 상대의 열정적인 반응을 통해 그 기쁨을 확대하는 것이 당신에게는 가장 자연스러운 공유 방식입니다. 함께 기뻐하는 순간이 관계의 에너지를 높이는 핵심 경험이며, 이것은 당신이 관계에서 긍정적 감정을 순환시키는 고유한 강점입니다.",
      "innerVoice": "'이 기쁨은 네가 같이 기뻐해줘야 진짜 완성돼.' — 당신의 내면은 좋은 감정을 나눌 때 관계가 가장 살아있다고 느낍니다.",
      "strength": "긍정적 감정을 관계 안에서 증폭시키는 능력이 탁월해요. 당신이 기쁨을 나눌 때의 에너지는 상대에게도 전파되어, 파트너 역시 '이 관계가 내 삶에 좋은 영향을 주고 있다'고 느끼게 합니다. 관계의 긍정 비율(positive-to-negative ratio)을 높이는 데 자연스럽게 기여합니다.",
      "blindSpot": "상대가 기대만큼 열정적으로 반응하지 않을 때 실망할 수 있어요. 파트너가 바쁘거나 지쳐 있어서 충분히 반응하지 못하는 상황을 '내 기쁨에 관심이 없다'로 해석하게 되는 순간이 있을 수 있습니다.",
      "comparison": "조용한 음미형이 기쁨을 내면에서 충분히 소화한 뒤 나누는 반면, 당신은 기쁨의 순간을 실시간으로 공유하면서 상대와의 정서적 동기화를 통해 경험을 완성합니다.",
      "checkQuestion": "혹시 좋은 소식을 전했는데 상대의 반응이 기대보다 담담했을 때, 기쁨이 반감되거나 서운한 느낌이 든 경험이 있나요?",
      "insight": "Gable 등(2004)의 연구에 따르면, 긍정적 사건을 파트너와 공유하고 상대로부터 적극적-구성적 반응(active-constructive responding)을 받을 때, 개인의 긍정 정서와 관계 만족도가 모두 높아집니다. 이 과정을 자본화(capitalization)라 하며, 연구는 좋은 일을 나누는 행위 자체가 그 경험의 가치를 높이는 독립적 효과가 있음을 보여줍니다. 다만 이 효과는 상대의 반응 질에 의존하므로, 파트너에게 자신이 원하는 반응 방식을 구체적으로 전달하는 것이 도움이 됩니다. 이 결과는 현재 시점의 경향성이며, 관계 경험과 맥락에 따라 변화할 수 있습니다.",
      "color": "#5B9BD5",
      "bg": "#EEF6FF"
    },
    "QUIET_SAVORING": {
      "emoji": "🍵",
      "title": "조용한 음미형",
      "description": "당신은 좋은 일이 생기면 먼저 혼자만의 시간 속에서 그 기쁨을 충분히 느끼고, 이후 연인과 깊이 있게 나누는 사람입니다. 즉각적 공유보다 감정의 의미를 곱씹은 뒤 나누는 것이 더 자연스러우며, 그 과정에서 기쁨이 더 풍부해진다고 느낍니다. 이것은 소극적 태도가 아니라, 감정을 깊이 처리하는 당신만의 공유 리듬입니다.",
      "innerVoice": "'이 기쁨의 의미를 충분히 느끼고 나서, 정말 중요한 사람과 나누고 싶어.' — 당신의 내면은 감정의 질을 중시하며, 나눔의 타이밍을 스스로 조율합니다.",
      "strength": "기쁨을 나눌 때 깊이 있는 대화를 이끌어내는 능력이 있어요. 단순한 축하 인사를 넘어, 그 경험이 서로에게 어떤 의미인지를 함께 탐색하는 시간을 만들기 때문에, 나눔의 순간이 관계에 깊은 유대감을 형성합니다.",
      "blindSpot": "혼자 기쁨을 소화하는 시간이 길어지면, 상대가 소외감을 느낄 수 있어요. 파트너가 '좋은 일이 있었는데 나에게 먼저 말하지 않았다'고 느끼면 신뢰에 작은 균열이 생길 수 있습니다.",
      "comparison": "적극적-구성적 반응형이 기쁨을 즉시 공유하여 에너지를 높이는 반면, 당신은 기쁨을 내면에서 숙성시킨 뒤 공유하여 깊이를 더합니다. 같은 기쁨이지만 나누는 속도와 질감이 다릅니다.",
      "checkQuestion": "혹시 좋은 일이 있었는데 바로 말하지 않아서, 나중에 연인이 '왜 바로 안 알려줬어?'라고 아쉬워한 경험이 있나요?",
      "insight": "Bryant와 Veroff(2007)의 음미(savoring) 연구에 따르면, 긍정적 경험을 의식적으로 음미하는 것은 주관적 안녕감을 높이는 독립적 요인입니다. Gable의 자본화 연구와 결합하면, 음미 후 공유하는 방식은 내적 긍정 효과(savoring)와 관계적 긍정 효과(capitalization)를 모두 얻을 수 있는 전략이 됩니다. 다만 공유의 지연이 파트너에게 배제감을 줄 수 있으므로, '지금 좋은 일이 있었는데, 만나서 자세히 이야기하고 싶어'처럼 공유 의사를 먼저 표시하는 것이 관계 만족도를 높이는 데 도움이 됩니다. 이 결과는 현재 시점의 경향성이며, 관계 경험과 맥락에 따라 변화할 수 있습니다.",
      "color": "#95A5A6",
      "bg": "#F4F6F6"
    },
    "PRACTICAL_GROUNDING": {
      "emoji": "📋",
      "title": "현실적 안정형",
      "description": "당신은 좋은 일이 생기면 기쁨을 느끼면서도 자연스럽게 '이것을 어떻게 잘 활용할까'를 함께 생각하는 사람입니다. 연인에게 소식을 전할 때도 감정 공유와 현실적 계획이 자연스럽게 연결됩니다. 이것은 냉정한 것이 아니라, 좋은 일을 실질적 가치로 전환하려는 당신의 실용적 사랑 언어입니다.",
      "innerVoice": "'기쁜 만큼, 이걸 우리에게 좋은 방향으로 잘 써먹고 싶어.' — 당신의 내면은 감정과 실용성을 분리하지 않으며, 좋은 일의 현실적 의미를 파트너와 함께 구체화하고 싶어 합니다.",
      "strength": "긍정적 사건을 관계의 실질적 발전으로 연결하는 데 능숙해요. 좋은 일을 단순히 기뻐하고 끝내는 것이 아니라, 그것이 두 사람의 미래에 어떤 의미를 갖는지 함께 정리하기 때문에 관계가 현실적으로 단단해지는 데 기여합니다.",
      "blindSpot": "감정 공유보다 계획 이야기가 먼저 나올 때, 상대가 '내 기쁨에 공감해주기보다 분석부터 한다'고 느낄 수 있어요. 파트너가 원하는 것이 해결책이 아니라 함께 기뻐하는 시간일 때, 타이밍의 차이가 발생할 수 있습니다.",
      "comparison": "조용한 음미형이 기쁨의 감정적 의미를 먼저 곱씹는 반면, 당신은 기쁨의 현실적 의미와 다음 단계를 먼저 떠올리며, 그 과정 자체가 기쁨을 나누는 방식이 됩니다.",
      "checkQuestion": "혹시 연인에게 좋은 소식을 전하면서 거의 동시에 '그래서 이제 이렇게 하면 좋겠다'는 계획을 말하다가, 상대가 '잠깐, 일단 기뻐하자'라고 한 경험이 있나요?",
      "insight": "Gable 등(2004)의 자본화 모델에서는 반응 유형을 적극적-구성적, 소극적-구성적, 적극적-파괴적, 소극적-파괴적으로 분류하며, 적극적-구성적 반응이 관계 만족도와 가장 강하게 연관됩니다. 현실적 안정형은 이 모델에서 구성적(constructive) 차원에 속하되 표현 방식이 다를 수 있습니다. Impett 등(2012)의 연구에 따르면, 파트너의 성취를 관계의 공동 자산으로 인식하는 경향은 관계 헌신도와 정적 상관을 보입니다. 감정 공유와 현실 계획의 순서를 파트너의 필요에 맞게 조율하면 두 가지 효과를 모두 얻을 수 있습니다. 이 결과는 현재 시점의 경향성이며, 관계 경험과 맥락에 따라 변화할 수 있습니다.",
      "color": "#FF7EB3",
      "bg": "#FFF0F7"
    },
    "RESERVED_PROCESSING": {
      "emoji": "🌊",
      "title": "내면 소화형",
      "description": "당신은 좋은 일이 생겼을 때 하나의 고정된 방식이 아니라, 상황과 감정의 종류에 따라 나누는 방식이 달라지는 사람입니다. 어떤 기쁨은 즉시 나누고, 어떤 기쁨은 혼자 충분히 느낀 뒤에 전하며, 또 어떤 기쁨은 현실적 맥락과 함께 이야기합니다. 다양한 공유 방식을 자유롭게 넘나드는 것이 당신의 고유한 패턴입니다.",
      "innerVoice": "'기쁜 일마다 나누고 싶은 방식이 조금씩 달라.' — 당신의 내면은 감정의 종류와 크기에 따라 공유의 타이밍과 방식을 직관적으로 조절합니다.",
      "strength": "기쁨의 성격에 맞는 공유 방식을 자연스럽게 선택할 수 있어요. 큰 성취는 적극적으로, 개인적 의미가 깊은 일은 조용히, 실질적 변화가 있는 일은 계획과 함께 나누기 때문에, 각 상황에서 가장 적절한 나눔이 이루어지는 편입니다.",
      "blindSpot": "공유 패턴이 일정하지 않기 때문에, 파트너가 당신의 기쁨에 어떻게 반응해야 할지 어려워할 수 있어요. 어떤 날은 적극적으로 나누고 어떤 날은 혼자 소화하는 모습에 상대가 일관된 반응 패턴을 찾지 못해 당혹감을 느낄 수 있습니다.",
      "comparison": "적극적-구성적 반응형, 조용한 음미형, 현실적 안정형이 각각 뚜렷한 공유 스타일을 가진 반면, 당신은 세 가지 방식을 기쁨의 종류에 따라 유동적으로 활용하며 자신만의 나눔 리듬을 만듭니다.",
      "checkQuestion": "혹시 비슷한 좋은 일인데 한 번은 바로 연인에게 전화하고, 다른 한 번은 며칠 뒤에 말하면서 스스로도 '나는 왜 이렇게 다르지?'라고 생각한 경험이 있나요?",
      "insight": "Gable 등(2004)의 연구는 자본화 과정의 효과가 공유 행위 자체보다 파트너의 반응 질(perceived responsiveness)에 더 크게 의존함을 보여줍니다. 다양한 공유 방식을 활용하는 것은 상황 적응력의 표현이며, Reis와 Shaver(1988)의 친밀감 과정 모델에서 강조하는 반응적 상호작용(responsive interaction)의 유연한 형태로 볼 수 있습니다. 이 유연성을 더 효과적으로 활용하려면, 파트너에게 '오늘은 같이 기뻐해줘' 또는 '이건 조용히 이야기하고 싶어'처럼 자신이 원하는 반응 방식을 미리 알려주는 것이 도움이 됩니다. 이 결과는 현재 시점의 경향성이며, 관계 경험과 맥락에 따라 변화할 수 있습니다.",
      "color": "#9B8FD4",
      "bg": "#EDE8FF"
    }
  }
}